jdesmos/__init__.py
jdesmos/jdesmos.py
jdesmos-0.0.4.dist-info/LICENSE
jdesmos-0.0.4.dist-info/METADATA
jdesmos-0.0.4.dist-info/WHEEL
jdesmos-0.0.4.dist-info/RECORD
